prompt2txt/__init__.py
prompt2txt/cli.py
prompt2txt/extractor.py
prompt2txt-0.2.0.dist-info/LICENSE
prompt2txt-0.2.0.dist-info/METADATA
prompt2txt-0.2.0.dist-info/WHEEL
prompt2txt-0.2.0.dist-info/entry_points.txt
prompt2txt-0.2.0.dist-info/RECORD
