Metadata-Version: 2.3
Name: prompt2txt
Version: 0.2.0
Summary: Extracts Draw Things and A1111 prompts to txt files cfrom PNG files in a specified  path, useful for captioning
License: GPLv3
Author: David Van de Ven
Author-email: zanshin.g1@gmail.com
Requires-Python: >=3.12
Classifier: License :: Other/Proprietary License
Classifier: Programming Language :: Python :: 3
Classifier: Programming Language :: Python :: 3.12
Classifier: Programming Language :: Python :: 3.13
Requires-Dist: pillow (>=11.1.0,<12.0.0)
Requires-Dist: tqdm (>=4.67.1,<5.0.0)
Project-URL: Issues, https://github.com/Zanshinmu/llava-caption/prompt2txt
Project-URL: Repository, https://github.com/Zanshinmu/prompt2txt
